pythonqwt-0.14.6.dist-info/licenses/LICENSE
qwt/__init__.py
qwt/_math.py
qwt/color_map.py
qwt/column_symbol.py
qwt/dyngrid_layout.py
qwt/graphic.py
qwt/interval.py
qwt/legend.py
qwt/null_paintdevice.py
qwt/painter.py
qwt/painter_command.py
qwt/plot.py
qwt/plot_canvas.py
qwt/plot_curve.py
qwt/plot_directpainter.py
qwt/plot_grid.py
qwt/plot_layout.py
qwt/plot_marker.py
qwt/plot_renderer.py
qwt/plot_series.py
qwt/qthelpers.py
qwt/scale_div.py
qwt/scale_draw.py
qwt/scale_engine.py
qwt/scale_map.py
qwt/scale_widget.py
qwt/symbol.py
qwt/text.py
qwt/toqimage.py
qwt/transform.py
qwt/tests/__init__.py
qwt/tests/comparative_benchmarks.py
qwt/tests/conftest.py
qwt/tests/test_backingstore.py
qwt/tests/test_bodedemo.py
qwt/tests/test_cartesian.py
qwt/tests/test_cpudemo.py
qwt/tests/test_curvebenchmark1.py
qwt/tests/test_curvebenchmark2.py
qwt/tests/test_curvedemo1.py
qwt/tests/test_curvedemo2.py
qwt/tests/test_data.py
qwt/tests/test_errorbar.py
qwt/tests/test_eventfilter.py
qwt/tests/test_highdpi.py
qwt/tests/test_image.py
qwt/tests/test_loadtest.py
qwt/tests/test_logcurve.py
qwt/tests/test_mapdemo.py
qwt/tests/test_multidemo.py
qwt/tests/test_relativemargin.py
qwt/tests/test_simple.py
qwt/tests/test_stylesheet.py
qwt/tests/test_symbols.py
qwt/tests/test_vertical.py
qwt/tests/utils.py
qwt/tests/data/PythonQwt.svg
qwt/tests/data/bodedemo.png
qwt/tests/data/cartesian.png
qwt/tests/data/cpudemo.png
qwt/tests/data/curvebenchmark1.png
qwt/tests/data/curvebenchmark2.png
qwt/tests/data/curvedemo1.png
qwt/tests/data/curvedemo2.png
qwt/tests/data/data.png
qwt/tests/data/errorbar.png
qwt/tests/data/eventfilter.png
qwt/tests/data/image.png
qwt/tests/data/loadtest.png
qwt/tests/data/logcurve.png
qwt/tests/data/mapdemo.png
qwt/tests/data/multidemo.png
qwt/tests/data/simple.png
qwt/tests/data/stylesheet.png
qwt/tests/data/symbol.svg
qwt/tests/data/symbols.png
qwt/tests/data/testlauncher.png
qwt/tests/data/vertical.png
pythonqwt-0.14.6.dist-info/METADATA
pythonqwt-0.14.6.dist-info/WHEEL
pythonqwt-0.14.6.dist-info/entry_points.txt
pythonqwt-0.14.6.dist-info/top_level.txt
pythonqwt-0.14.6.dist-info/RECORD
