Metadata-Version: 2.4
Name: PythonQwt
Version: 0.14.6
Summary: Qt plotting widgets for Python
Author-email: Pierre Raybaut <pierre.raybaut@gmail.com>
License: PythonQwt License Agreement
Project-URL: Homepage, https://github.com/PlotPyStack/PythonQwt/
Project-URL: Documentation, https://PythonQwt.readthedocs.io/en/latest/
Classifier: Topic :: Scientific/Engineering
Classifier: Topic :: Scientific/Engineering :: Visualization
Classifier: Topic :: Software Development :: Widget Sets
Classifier: Topic :: Software Development :: Libraries :: Python Modules
Classifier: Topic :: Utilities
Classifier: Topic :: Scientific/Engineering
Classifier: Topic :: Scientific/Engineering :: Human Machine Interfaces
Classifier: Topic :: Software Development :: User Interfaces
Classifier: Operating System :: MacOS
Classifier: Operating System :: Microsoft :: Windows
Classifier: Operating System :: OS Independent
Classifier: Operating System :: POSIX
Classifier: Operating System :: Unix
Classifier: Programming Language :: Python :: 3.9
Classifier: Programming Language :: Python :: 3.10
Classifier: Programming Language :: Python :: 3.11
Classifier: Programming Language :: Python :: 3.12
Classifier: Programming Language :: Python :: 3.13
Requires-Python: <4,>=3.9
License-File: LICENSE
Requires-Dist: NumPy>=1.19
Requires-Dist: QtPy>=1.9
Provides-Extra: dev
Requires-Dist: ruff; extra == "dev"
Requires-Dist: pylint; extra == "dev"
Requires-Dist: Coverage; extra == "dev"
Provides-Extra: doc
Requires-Dist: PyQt5; extra == "doc"
Requires-Dist: sphinx>6; extra == "doc"
Requires-Dist: python-docs-theme; extra == "doc"
Provides-Extra: test
Requires-Dist: pytest; extra == "test"
Requires-Dist: pytest-xvfb; extra == "test"
Dynamic: license-file
